pyorderbook/__init__.py
pyorderbook/book.py
pyorderbook/level.py
pyorderbook/order.py
pyorderbook/trade_blotter.py
pyorderbook-0.4.9.dist-info/METADATA
pyorderbook-0.4.9.dist-info/WHEEL
pyorderbook-0.4.9.dist-info/licenses/LICENSE
pyorderbook-0.4.9.dist-info/RECORD
