Metadata-Version: 2.4
Name: pyorderbook
Version: 0.4.9
Summary: Order Book and Matching Engine
Project-URL: Repository, https://github.com/zkhorozianbc/pyorderbook
Author-email: Zach Khorozian <zkhorozianbc@gmail.com>
License: MIT License
License-File: LICENSE
Keywords: limit order book,matching engine,order book,orderbook,pyorderbook
Classifier: License :: OSI Approved :: MIT License
Classifier: Operating System :: OS Independent
Classifier: Programming Language :: Python :: 3
Classifier: Programming Language :: Python :: 3.11
Classifier: Programming Language :: Python :: 3.12
Classifier: Programming Language :: Python :: 3.13
Requires-Python: >=3.11
